CHANGELOG.md
majormode/__init__.py
majormode/perseus/__init__.py
majormode/perseus/agent/__init__.py
majormode/perseus/agent/email_address_verification_agent.py
majormode/perseus/agent/email_sender_agent.py
majormode/perseus/bootstrap/__init__.py
majormode/perseus/bootstrap/tornado_handler.py
majormode/perseus/db/create_currency_dataset.sql
majormode/perseus/db/create_exception_function.sql
majormode/perseus/db/create_geometry_function.sql
majormode/perseus/db/create_label_type.sql
majormode/perseus/db/create_locale_function.sql
majormode/perseus/db/create_object_constant.sql
majormode/perseus/db/create_object_table.sql
majormode/perseus/db/create_visibility_constant.sql
majormode/perseus/manage.py
majormode/perseus/service/__init__.py
majormode/perseus/service/account/__init__.py
majormode/perseus/service/account/account_service.py
majormode/perseus/service/account/contact_service.py
majormode/perseus/service/account/db/create_account_constraint.sql
majormode/perseus/service/account/db/create_account_function.sql
majormode/perseus/service/account/db/create_account_index.sql
majormode/perseus/service/account/db/create_account_table.sql
majormode/perseus/service/account/db/create_session_constraint.sql
majormode/perseus/service/account/db/create_session_function.sql
majormode/perseus/service/account/db/create_session_index.sql
majormode/perseus/service/account/db/create_session_table.sql
majormode/perseus/service/account/db/migrate_account_table.718.sql
majormode/perseus/service/account/db/migrate_account_table@1.11.9.sql
majormode/perseus/service/account/db/migrate_account_table@1.12.0.sql
majormode/perseus/service/account/db/migrate_account_table@1.12.9.sql
majormode/perseus/service/account/db/migrate_account_table@1.17.14.sql
majormode/perseus/service/account/db/migrate_account_table@1.17.31.sql
majormode/perseus/service/account/db/migrate_account_table@1.21.0.sql
majormode/perseus/service/account/db/migrate_account_table@1.22.0.sql
perseus_restful_api_framework-1.28.15.dist-info/LICENSE.md
perseus_restful_api_framework-1.28.15.dist-info/METADATA
perseus_restful_api_framework-1.28.15.dist-info/WHEEL
perseus_restful_api_framework-1.28.15.dist-info/RECORD
