Metadata-Version: 2.1
Name: perseus-restful-api-framework
Version: 1.28.15
Summary: Python server framework for quickly building RESTful APIs with minimal effort
Home-page: https://github.com/majormode/perseus-restful-api-server-framework
License: Proprietary
Keywords: perseus,resful,api,server,framework
Author: Daniel CAUNE
Author-email: daniel.caune@gmail.com
Requires-Python: >=3.10
Classifier: Development Status :: 5 - Production/Stable
Classifier: License :: Other/Proprietary License
Classifier: Operating System :: OS Independent
Classifier: Programming Language :: Python
Classifier: Programming Language :: Python :: 3
Classifier: Programming Language :: Python :: 3.10
Classifier: Programming Language :: Python :: 3.11
Classifier: Programming Language :: Python :: 3.12
Classifier: Programming Language :: Python :: 3.13
Classifier: Topic :: Software Development :: Libraries
Requires-Dist: perseus-core-library (>=1.20.5,<2.0.0)
Requires-Dist: perseus-getenv-library (>=1.0.5,<2.0.0)
Requires-Dist: perseus-microrm-library (>=1.3.9,<2.0.0)
Requires-Dist: pillow (>=10.4.0,<11.0.0)
Requires-Dist: prosoponym (>=1.2.4,<2.0.0)
Requires-Dist: psutil (>=5.9,<6.0)
Requires-Dist: pymemcache (>=4.0.0,<5.0.0)
Requires-Dist: setuptools (>=75.1.0,<76.0.0)
Requires-Dist: tornado (>=6.4.1,<7.0.0)
Project-URL: Repository, https://github.com/majormode/perseus-restful-api-server-framework
